odoo/addons/base_territory/README.rst
odoo/addons/base_territory/__init__.py
odoo/addons/base_territory/__manifest__.py
odoo/addons/base_territory/demo/base_territory_demo.xml
odoo/addons/base_territory/i18n/base_territory.pot
odoo/addons/base_territory/i18n/es.po
odoo/addons/base_territory/i18n/es_AR.po
odoo/addons/base_territory/i18n/it.po
odoo/addons/base_territory/i18n/pl.po
odoo/addons/base_territory/i18n/pt_BR.po
odoo/addons/base_territory/i18n/tr.po
odoo/addons/base_territory/models/__init__.py
odoo/addons/base_territory/models/res_branch.py
odoo/addons/base_territory/models/res_country.py
odoo/addons/base_territory/models/res_district.py
odoo/addons/base_territory/models/res_region.py
odoo/addons/base_territory/models/res_territory.py
odoo/addons/base_territory/readme/CONTRIBUTORS.md
odoo/addons/base_territory/readme/CREDITS.md
odoo/addons/base_territory/readme/DESCRIPTION.md
odoo/addons/base_territory/readme/USAGE.md
odoo/addons/base_territory/security/ir.model.access.csv
odoo/addons/base_territory/static/description/icon.png
odoo/addons/base_territory/static/description/index.html
odoo/addons/base_territory/tests/__init__.py
odoo/addons/base_territory/tests/test_res_branch.py
odoo/addons/base_territory/tests/test_res_country.py
odoo/addons/base_territory/tests/test_res_district.py
odoo/addons/base_territory/tests/test_res_region.py
odoo/addons/base_territory/tests/test_res_territory.py
odoo/addons/base_territory/views/menu.xml
odoo/addons/base_territory/views/res_branch.xml
odoo/addons/base_territory/views/res_country.xml
odoo/addons/base_territory/views/res_district.xml
odoo/addons/base_territory/views/res_region.xml
odoo/addons/base_territory/views/res_territory.xml
odoo_addon_base_territory-18.0.1.0.0.5.dist-info/METADATA
odoo_addon_base_territory-18.0.1.0.0.5.dist-info/WHEEL
odoo_addon_base_territory-18.0.1.0.0.5.dist-info/top_level.txt
odoo_addon_base_territory-18.0.1.0.0.5.dist-info/RECORD
